pandas_toolkit/__init__.py
pandas_toolkit/data_utils.py
pandas_toolkit/operations.py
pandas_toolkit/summaries.py
pandas_toolkit_bharath-0.1.0.dist-info/METADATA
pandas_toolkit_bharath-0.1.0.dist-info/WHEEL
pandas_toolkit_bharath-0.1.0.dist-info/top_level.txt
pandas_toolkit_bharath-0.1.0.dist-info/RECORD
