Metadata-Version: 2.4
Name: pandas-toolkit-bharath
Version: 0.1.0
Summary: Simplified Pandas data preprocessing with menu-based interaction
Author: Bharath Kumar
Requires-Python: >=3.7
Requires-Dist: pandas
Requires-Dist: scikit-learn
Dynamic: author
Dynamic: requires-dist
Dynamic: requires-python
Dynamic: summary
